{
"type": "FeatureCollection",
"name": "airportpt",
"crs": { "type": "name", "properties": { "name": "urn:ogc:def:crs:OGC:1.3:CRS84" } },
"features": [
{ "type": "Feature", "properties": { "id": 1, "pointfield": "Boston Logan Airport" }, "geometry": { "type": "Point", "coordinates": [ -71.019217896791488, 42.366200924310768 ] } }
]
}
